safelyx/__init__.py
safelyx-0.1.1.dist-info/LICENSE
safelyx-0.1.1.dist-info/METADATA
safelyx-0.1.1.dist-info/WHEEL
safelyx-0.1.1.dist-info/top_level.txt
safelyx-0.1.1.dist-info/RECORD
