Metadata-Version: 2.2
Name: safelyx
Version: 0.1.1
Summary: API client for Safelyx.
Author-email: Safelyx <help@safelyx.com>
License: ISC
Project-URL: Homepage, https://github.com/safelyx/safelyx-py
Project-URL: Download, https://github.com/safelyx/safelyx-py/archive/refs/tags/v0.1.1.tar.gz
Keywords: safelyx,api,client,sdk,security,automated moderation tools,content moderation,message moderation,image moderation,link safety check,email verification,ugc moderation,user-generated content moderation,content safety,content safety tools,content safety api,content safety sdk,content safety client
Requires-Python: >=3.11
License-File: LICENSE
Requires-Dist: requests==2.32.3
